BeginnersbookCJiaochengChuyi/README.md
BeginnersbookCJiaochengChuyi/__init__.py
BeginnersbookCJiaochengChuyi/__main__.py
BeginnersbookCJiaochengChuyi/file.epub
BeginnersbookCJiaochengChuyi/index.html
BeginnersbookCJiaochengChuyi/css/__init__.py
BeginnersbookCJiaochengChuyi/css/annotations.css
BeginnersbookCJiaochengChuyi/css/main.css
BeginnersbookCJiaochengChuyi/css/normalize.css
BeginnersbookCJiaochengChuyi/css/popup.css
BeginnersbookCJiaochengChuyi/font/__init__.py
BeginnersbookCJiaochengChuyi/font/fontello.eot
BeginnersbookCJiaochengChuyi/font/fontello.svg
BeginnersbookCJiaochengChuyi/font/fontello.ttf
BeginnersbookCJiaochengChuyi/font/fontello.woff
BeginnersbookCJiaochengChuyi/img/__init__.py
BeginnersbookCJiaochengChuyi/img/annotator-glyph-sprite.png
BeginnersbookCJiaochengChuyi/img/annotator-icon-sprite.png
BeginnersbookCJiaochengChuyi/img/apple-touch-icon.png
BeginnersbookCJiaochengChuyi/img/cancelfullscreen.png
BeginnersbookCJiaochengChuyi/img/close.png
BeginnersbookCJiaochengChuyi/img/fullscreen.png
BeginnersbookCJiaochengChuyi/img/loader.gif
BeginnersbookCJiaochengChuyi/img/menu-icon.png
BeginnersbookCJiaochengChuyi/img/save.png
BeginnersbookCJiaochengChuyi/img/saved.png
BeginnersbookCJiaochengChuyi/img/settings-s.png
BeginnersbookCJiaochengChuyi/img/settings.png
BeginnersbookCJiaochengChuyi/img/star.png
BeginnersbookCJiaochengChuyi/js/__init__.py
BeginnersbookCJiaochengChuyi/js/epub.js
BeginnersbookCJiaochengChuyi/js/epub.min.js
BeginnersbookCJiaochengChuyi/js/epub.min.map
BeginnersbookCJiaochengChuyi/js/hooks.min.js
BeginnersbookCJiaochengChuyi/js/hooks.min.map
BeginnersbookCJiaochengChuyi/js/reader.js
BeginnersbookCJiaochengChuyi/js/reader.js.map
BeginnersbookCJiaochengChuyi/js/reader.min.js
BeginnersbookCJiaochengChuyi/js/reader.min.map
BeginnersbookCJiaochengChuyi/js/hooks/__init__.py
BeginnersbookCJiaochengChuyi/js/hooks/extensions/__init__.py
BeginnersbookCJiaochengChuyi/js/hooks/extensions/highlight.js
beginnersbook_c_jiaocheng_chuyi-2024.3.4.0.dist-info/METADATA
beginnersbook_c_jiaocheng_chuyi-2024.3.4.0.dist-info/WHEEL
beginnersbook_c_jiaocheng_chuyi-2024.3.4.0.dist-info/entry_points.txt
beginnersbook_c_jiaocheng_chuyi-2024.3.4.0.dist-info/top_level.txt
beginnersbook_c_jiaocheng_chuyi-2024.3.4.0.dist-info/RECORD
